modules/__init__.py
modules/domain_info.py
modules/email_info.py
modules/ip_info.py
modules/phone_info.py
modules/report_generator.py
modules/username_info.py
modules/visualization.py
osher/__init__.py
osher/config.py
osher/main.py
osher/osint_scout.py
osher/web_interface.py
osher/modules/__init__.py
osher/modules/domain_info.py
osher/modules/email_info.py
osher/modules/ip_info.py
osher/modules/phone_info.py
osher/modules/report_generator.py
osher/modules/username_info.py
osher/modules/visualization.py
osher/utils/__init__.py
osher/utils/api_helper.py
osher/utils/data_formatter.py
osher/utils/input_validator.py
osher-0.1.0.dist-info/licenses/LICENSE
utils/__init__.py
utils/api_helper.py
utils/data_formatter.py
utils/input_validator.py
osher-0.1.0.dist-info/METADATA
osher-0.1.0.dist-info/WHEEL
osher-0.1.0.dist-info/entry_points.txt
osher-0.1.0.dist-info/top_level.txt
osher-0.1.0.dist-info/RECORD
