Metadata-Version: 2.4
Name: osher
Version: 0.1.0
Summary: A comprehensive OSINT (Open Source Intelligence) tool with multiple data sources
Home-page: https://github.com/osintscout/osher
Author: OSINT Scout Team
Author-email: info@osintscout.com
Classifier: Programming Language :: Python :: 3
Classifier: License :: OSI Approved :: MIT License
Classifier: Operating System :: OS Independent
Classifier: Topic :: Security
Classifier: Topic :: Internet
Requires-Python: >=3.7
License-File: LICENSE
Requires-Dist: click
Requires-Dist: dnspython
Requires-Dist: email-validator
Requires-Dist: flask
Requires-Dist: flask-sqlalchemy
Requires-Dist: gunicorn
Requires-Dist: matplotlib
Requires-Dist: numpy
Requires-Dist: pandas
Requires-Dist: phonenumbers
Requires-Dist: psycopg2-binary
Requires-Dist: pyopenssl
Requires-Dist: python-whois
Requires-Dist: requests
Requires-Dist: rich
Requires-Dist: seaborn
Requires-Dist: whois
Dynamic: author
Dynamic: author-email
Dynamic: classifier
Dynamic: description
Dynamic: description-content-type
Dynamic: home-page
Dynamic: license-file
Dynamic: requires-dist
Dynamic: requires-python
Dynamic: summary
